{"04981":{"id":"04981","name":"Thanh Hà","slug":"thanh-ha","fullName":"Thị trấn Thanh Hà","level":"Thị trấn","parentId":"159"},"05074":{"id":"05074","name":"Thanh Nông","slug":"thanh-nong","fullName":"Xã Thanh Nông","level":"Xã","parentId":"159"},"05392":{"id":"05392","name":"Chi Nê","slug":"chi-ne","fullName":"Thị trấn Chi Nê","level":"Thị trấn","parentId":"159"},"05395":{"id":"05395","name":"Phú Lão","slug":"phu-lao","fullName":"Xã Phú Lão","level":"Xã","parentId":"159"},"05398":{"id":"05398","name":"Phú Thành","slug":"phu-thanh","fullName":"Xã Phú Thành","level":"Xã","parentId":"159"},"05401":{"id":"05401","name":"Cố Nghĩa","slug":"co-nghia","fullName":"Xã Cố Nghĩa","level":"Xã","parentId":"159"},"05404":{"id":"05404","name":"Hưng Thi","slug":"hung-thi","fullName":"Xã Hưng Thi","level":"Xã","parentId":"159"},"05407":{"id":"05407","name":"Lạc Long","slug":"lac-long","fullName":"Xã Lạc Long","level":"Xã","parentId":"159"},"05410":{"id":"05410","name":"Liên Hòa","slug":"lien-hoa","fullName":"Xã Liên Hòa","level":"Xã","parentId":"159"},"05413":{"id":"05413","name":"Khoan Dụ","slug":"khoan-du","fullName":"Xã Khoan Dụ","level":"Xã","parentId":"159"},"05416":{"id":"05416","name":"Đồng Môn","slug":"dong-mon","fullName":"Xã Đồng Môn","level":"Xã","parentId":"159"},"05419":{"id":"05419","name":"Đồng Tâm","slug":"dong-tam","fullName":"Xã Đồng Tâm","level":"Xã","parentId":"159"},"05422":{"id":"05422","name":"Yên Bồng","slug":"yen-bong","fullName":"Xã Yên Bồng","level":"Xã","parentId":"159"},"05425":{"id":"05425","name":"An Lạc","slug":"an-lac","fullName":"Xã An Lạc","level":"Xã","parentId":"159"},"05428":{"id":"05428","name":"An Bình","slug":"an-binh","fullName":"Xã An Bình","level":"Xã","parentId":"159"}}