{"12688":{"id":"12688","name":"Đông Hưng","slug":"dong-hung","fullName":"Thị trấn Đông Hưng","level":"Thị trấn","parentId":"340"},"12691":{"id":"12691","name":"Đô Lương","slug":"do-luong","fullName":"Xã Đô Lương","level":"Xã","parentId":"340"},"12694":{"id":"12694","name":"Đông Phương","slug":"dong-phuong","fullName":"Xã Đông Phương","level":"Xã","parentId":"340"},"12697":{"id":"12697","name":"Liên Giang","slug":"lien-giang","fullName":"Xã Liên Giang","level":"Xã","parentId":"340"},"12700":{"id":"12700","name":"An Châu","slug":"an-chau","fullName":"Xã An Châu","level":"Xã","parentId":"340"},"12703":{"id":"12703","name":"Đông Sơn","slug":"dong-son","fullName":"Xã Đông Sơn","level":"Xã","parentId":"340"},"12706":{"id":"12706","name":"Đông Cường","slug":"dong-cuong","fullName":"Xã Đông Cường","level":"Xã","parentId":"340"},"12709":{"id":"12709","name":"Phú Lương","slug":"phu-luong","fullName":"Xã Phú Lương","level":"Xã","parentId":"340"},"12712":{"id":"12712","name":"Mê Linh","slug":"me-linh","fullName":"Xã Mê Linh","level":"Xã","parentId":"340"},"12715":{"id":"12715","name":"Lô Giang","slug":"lo-giang","fullName":"Xã Lô Giang","level":"Xã","parentId":"340"},"12718":{"id":"12718","name":"Đông La","slug":"dong-la","fullName":"Xã Đông La","level":"Xã","parentId":"340"},"12721":{"id":"12721","name":"Minh Tân","slug":"minh-tan","fullName":"Xã Minh Tân","level":"Xã","parentId":"340"},"12724":{"id":"12724","name":"Đông Xá","slug":"dong-xa","fullName":"Xã Đông Xá","level":"Xã","parentId":"340"},"12727":{"id":"12727","name":"Chương Dương","slug":"chuong-duong","fullName":"Xã Chương Dương","level":"Xã","parentId":"340"},"12730":{"id":"12730","name":"Nguyên Xá","slug":"nguyen-xa","fullName":"Xã Nguyên Xá","level":"Xã","parentId":"340"},"12733":{"id":"12733","name":"Phong Châu","slug":"phong-chau","fullName":"Xã Phong Châu","level":"Xã","parentId":"340"},"12736":{"id":"12736","name":"Hợp Tiến","slug":"hop-tien","fullName":"Xã Hợp Tiến","level":"Xã","parentId":"340"},"12739":{"id":"12739","name":"Hồng Việt","slug":"hong-viet","fullName":"Xã Hồng Việt","level":"Xã","parentId":"340"},"12742":{"id":"12742","name":"Đông Hà","slug":"dong-ha","fullName":"Xã Đông Hà","level":"Xã","parentId":"340"},"12745":{"id":"12745","name":"Đông Giang","slug":"dong-giang","fullName":"Xã Đông Giang","level":"Xã","parentId":"340"},"12748":{"id":"12748","name":"Đông Kinh","slug":"dong-kinh","fullName":"Xã Đông Kinh","level":"Xã","parentId":"340"},"12751":{"id":"12751","name":"Đông Hợp","slug":"dong-hop","fullName":"Xã Đông Hợp","level":"Xã","parentId":"340"},"12754":{"id":"12754","name":"Thăng Long","slug":"thang-long","fullName":"Xã Thăng Long","level":"Xã","parentId":"340"},"12757":{"id":"12757","name":"Đông Các","slug":"dong-cac","fullName":"Xã Đông Các","level":"Xã","parentId":"340"},"12760":{"id":"12760","name":"Phú Châu","slug":"phu-chau","fullName":"Xã Phú Châu","level":"Xã","parentId":"340"},"12763":{"id":"12763","name":"Hoa Lư","slug":"hoa-lu","fullName":"Xã Hoa Lư","level":"Xã","parentId":"340"},"12766":{"id":"12766","name":"Minh Châu","slug":"minh-chau","fullName":"Xã Minh Châu","level":"Xã","parentId":"340"},"12769":{"id":"12769","name":"Đông Tân","slug":"dong-tan","fullName":"Xã Đông Tân","level":"Xã","parentId":"340"},"12772":{"id":"12772","name":"Đông Vinh","slug":"dong-vinh","fullName":"Xã Đông Vinh","level":"Xã","parentId":"340"},"12775":{"id":"12775","name":"Đông Động","slug":"dong-dong","fullName":"Xã Đông Động","level":"Xã","parentId":"340"},"12778":{"id":"12778","name":"Hồng Châu","slug":"hong-chau","fullName":"Xã Hồng Châu","level":"Xã","parentId":"340"},"12781":{"id":"12781","name":"Bạch Đằng","slug":"bach-dang","fullName":"Xã Bạch Đằng","level":"Xã","parentId":"340"},"12784":{"id":"12784","name":"Trọng Quan","slug":"trong-quan","fullName":"Xã Trọng Quan","level":"Xã","parentId":"340"},"12787":{"id":"12787","name":"Hoa Nam","slug":"hoa-nam","fullName":"Xã Hoa Nam","level":"Xã","parentId":"340"},"12790":{"id":"12790","name":"Hồng Giang","slug":"hong-giang","fullName":"Xã Hồng Giang","level":"Xã","parentId":"340"},"12793":{"id":"12793","name":"Đông Phong","slug":"dong-phong","fullName":"Xã Đông Phong","level":"Xã","parentId":"340"},"12796":{"id":"12796","name":"Đông Quang","slug":"dong-quang","fullName":"Xã Đông Quang","level":"Xã","parentId":"340"},"12799":{"id":"12799","name":"Đông Xuân","slug":"dong-xuan","fullName":"Xã Đông Xuân","level":"Xã","parentId":"340"},"12802":{"id":"12802","name":"Đông Á","slug":"dong-a","fullName":"Xã Đông Á","level":"Xã","parentId":"340"},"12805":{"id":"12805","name":"Đông Lĩnh","slug":"dong-linh","fullName":"Xã Đông Lĩnh","level":"Xã","parentId":"340"},"12808":{"id":"12808","name":"Đông Hoàng","slug":"dong-hoang","fullName":"Xã Đông Hoàng","level":"Xã","parentId":"340"},"12811":{"id":"12811","name":"Đông Dương","slug":"dong-duong","fullName":"Xã Đông Dương","level":"Xã","parentId":"340"},"12814":{"id":"12814","name":"Đông Huy","slug":"dong-huy","fullName":"Xã Đông Huy","level":"Xã","parentId":"340"},"12823":{"id":"12823","name":"Đồng Phú","slug":"dong-phu","fullName":"Xã Đồng Phú","level":"Xã","parentId":"340"}}