{"13708":{"id":"13708","name":"Mỹ Lộc","slug":"my-loc","fullName":"Thị trấn Mỹ Lộc","level":"Thị trấn","parentId":"358"},"13711":{"id":"13711","name":"Mỹ Hà","slug":"my-ha","fullName":"Xã Mỹ Hà","level":"Xã","parentId":"358"},"13714":{"id":"13714","name":"Mỹ Tiến","slug":"my-tien","fullName":"Xã Mỹ Tiến","level":"Xã","parentId":"358"},"13717":{"id":"13717","name":"Mỹ Thắng","slug":"my-thang","fullName":"Xã Mỹ Thắng","level":"Xã","parentId":"358"},"13720":{"id":"13720","name":"Mỹ Trung","slug":"my-trung","fullName":"Xã Mỹ Trung","level":"Xã","parentId":"358"},"13723":{"id":"13723","name":"Mỹ Tân","slug":"my-tan","fullName":"Xã Mỹ Tân","level":"Xã","parentId":"358"},"13726":{"id":"13726","name":"Mỹ Phúc","slug":"my-phuc","fullName":"Xã Mỹ Phúc","level":"Xã","parentId":"358"},"13729":{"id":"13729","name":"Mỹ Hưng","slug":"my-hung","fullName":"Xã Mỹ Hưng","level":"Xã","parentId":"358"},"13732":{"id":"13732","name":"Mỹ Thuận","slug":"my-thuan","fullName":"Xã Mỹ Thuận","level":"Xã","parentId":"358"},"13735":{"id":"13735","name":"Mỹ Thịnh","slug":"my-thinh","fullName":"Xã Mỹ Thịnh","level":"Xã","parentId":"358"},"13738":{"id":"13738","name":"Mỹ Thành","slug":"my-thanh","fullName":"Xã Mỹ Thành","level":"Xã","parentId":"358"}}