{"14362":{"id":"14362","name":"Bắc Sơn","slug":"bac-son","fullName":"Phường Bắc Sơn","level":"Phường","parentId":"370"},"14365":{"id":"14365","name":"Trung Sơn","slug":"trung-son","fullName":"Phường Trung Sơn","level":"Phường","parentId":"370"},"14368":{"id":"14368","name":"Nam Sơn","slug":"nam-son","fullName":"Phường Nam Sơn","level":"Phường","parentId":"370"},"14369":{"id":"14369","name":"Tây Sơn","slug":"tay-son","fullName":"Phường Tây Sơn","level":"Phường","parentId":"370"},"14371":{"id":"14371","name":"Yên Sơn","slug":"yen-son","fullName":"Xã Yên Sơn","level":"Xã","parentId":"370"},"14374":{"id":"14374","name":"Yên Bình","slug":"yen-binh","fullName":"Phường Yên Bình","level":"Phường","parentId":"370"},"14375":{"id":"14375","name":"Tân Bình","slug":"tan-binh","fullName":"Phường Tân Bình","level":"Phường","parentId":"370"},"14377":{"id":"14377","name":"Quang Sơn","slug":"quang-son","fullName":"Xã Quang Sơn","level":"Xã","parentId":"370"},"14380":{"id":"14380","name":"Đông Sơn","slug":"dong-son","fullName":"Xã Đông Sơn","level":"Xã","parentId":"370"}}