{"14845":{"id":"14845","name":"Mường Lát","slug":"muong-lat","fullName":"Thị trấn Mường Lát","level":"Thị trấn","parentId":"384"},"14848":{"id":"14848","name":"Tam Chung","slug":"tam-chung","fullName":"Xã Tam Chung","level":"Xã","parentId":"384"},"14854":{"id":"14854","name":"Mường Lý","slug":"muong-ly","fullName":"Xã Mường Lý","level":"Xã","parentId":"384"},"14857":{"id":"14857","name":"Trung Lý","slug":"trung-ly","fullName":"Xã Trung Lý","level":"Xã","parentId":"384"},"14860":{"id":"14860","name":"Quang Chiểu","slug":"quang-chieu","fullName":"Xã Quang Chiểu","level":"Xã","parentId":"384"},"14863":{"id":"14863","name":"Pù Nhi","slug":"pu-nhi","fullName":"Xã Pù Nhi","level":"Xã","parentId":"384"},"14864":{"id":"14864","name":"Nhi Sơn","slug":"nhi-son","fullName":"Xã Nhi Sơn","level":"Xã","parentId":"384"},"14866":{"id":"14866","name":"Mường Chanh","slug":"muong-chanh","fullName":"Xã Mường Chanh","level":"Xã","parentId":"384"}}