{"16941":{"id":"16941","name":"Nghĩa Đàn","slug":"nghia-dan","fullName":"Thị trấn Nghĩa Đàn","level":"Thị trấn","parentId":"419"},"16942":{"id":"16942","name":"Nghĩa Mai","slug":"nghia-mai","fullName":"Xã Nghĩa Mai","level":"Xã","parentId":"419"},"16945":{"id":"16945","name":"Nghĩa Yên","slug":"nghia-yen","fullName":"Xã Nghĩa Yên","level":"Xã","parentId":"419"},"16948":{"id":"16948","name":"Nghĩa Lạc","slug":"nghia-lac","fullName":"Xã Nghĩa Lạc","level":"Xã","parentId":"419"},"16951":{"id":"16951","name":"Nghĩa Lâm","slug":"nghia-lam","fullName":"Xã Nghĩa Lâm","level":"Xã","parentId":"419"},"16954":{"id":"16954","name":"Nghĩa Sơn","slug":"nghia-son","fullName":"Xã Nghĩa Sơn","level":"Xã","parentId":"419"},"16957":{"id":"16957","name":"Nghĩa Lợi","slug":"nghia-loi","fullName":"Xã Nghĩa Lợi","level":"Xã","parentId":"419"},"16960":{"id":"16960","name":"Nghĩa Bình","slug":"nghia-binh","fullName":"Xã Nghĩa Bình","level":"Xã","parentId":"419"},"16963":{"id":"16963","name":"Nghĩa Thọ","slug":"nghia-tho","fullName":"Xã Nghĩa Thọ","level":"Xã","parentId":"419"},"16966":{"id":"16966","name":"Nghĩa Minh","slug":"nghia-minh","fullName":"Xã Nghĩa Minh","level":"Xã","parentId":"419"},"16969":{"id":"16969","name":"Nghĩa Phú","slug":"nghia-phu","fullName":"Xã Nghĩa Phú","level":"Xã","parentId":"419"},"16972":{"id":"16972","name":"Nghĩa Hưng","slug":"nghia-hung","fullName":"Xã Nghĩa Hưng","level":"Xã","parentId":"419"},"16975":{"id":"16975","name":"Nghĩa Hồng","slug":"nghia-hong","fullName":"Xã Nghĩa Hồng","level":"Xã","parentId":"419"},"16978":{"id":"16978","name":"Nghĩa Thịnh","slug":"nghia-thinh","fullName":"Xã Nghĩa Thịnh","level":"Xã","parentId":"419"},"16981":{"id":"16981","name":"Nghĩa Trung","slug":"nghia-trung","fullName":"Xã Nghĩa Trung","level":"Xã","parentId":"419"},"16984":{"id":"16984","name":"Nghĩa Hội","slug":"nghia-hoi","fullName":"Xã Nghĩa Hội","level":"Xã","parentId":"419"},"16987":{"id":"16987","name":"Nghĩa Tân","slug":"nghia-tan","fullName":"Xã Nghĩa Tân","level":"Xã","parentId":"419"},"16990":{"id":"16990","name":"Nghĩa Thắng","slug":"nghia-thang","fullName":"Xã Nghĩa Thắng","level":"Xã","parentId":"419"},"16996":{"id":"16996","name":"Nghĩa Hiếu","slug":"nghia-hieu","fullName":"Xã Nghĩa Hiếu","level":"Xã","parentId":"419"},"16999":{"id":"16999","name":"Nghĩa Liên","slug":"nghia-lien","fullName":"Xã Nghĩa Liên","level":"Xã","parentId":"419"},"17020":{"id":"17020","name":"Nghĩa Đức","slug":"nghia-duc","fullName":"Xã Nghĩa Đức","level":"Xã","parentId":"419"},"17023":{"id":"17023","name":"Nghĩa An","slug":"nghia-an","fullName":"Xã Nghĩa An","level":"Xã","parentId":"419"},"17026":{"id":"17026","name":"Nghĩa Long","slug":"nghia-long","fullName":"Xã Nghĩa Long","level":"Xã","parentId":"419"},"17029":{"id":"17029","name":"Nghĩa Lộc","slug":"nghia-loc","fullName":"Xã Nghĩa Lộc","level":"Xã","parentId":"419"},"17032":{"id":"17032","name":"Nghĩa Khánh","slug":"nghia-khanh","fullName":"Xã Nghĩa Khánh","level":"Xã","parentId":"419"}}