{"19495":{"id":"19495","name":"Gio Linh","slug":"gio-linh","fullName":"Thị trấn Gio Linh","level":"Thị trấn","parentId":"466"},"19496":{"id":"19496","name":"Cửa Việt","slug":"cua-viet","fullName":"Thị trấn Cửa Việt","level":"Thị trấn","parentId":"466"},"19498":{"id":"19498","name":"Trung Giang","slug":"trung-giang","fullName":"Xã Trung Giang","level":"Xã","parentId":"466"},"19501":{"id":"19501","name":"Trung Hải","slug":"trung-hai","fullName":"Xã Trung Hải","level":"Xã","parentId":"466"},"19504":{"id":"19504","name":"Trung Sơn","slug":"trung-son","fullName":"Xã Trung Sơn","level":"Xã","parentId":"466"},"19507":{"id":"19507","name":"Gio Phong","slug":"gio-phong","fullName":"Xã Gio Phong","level":"Xã","parentId":"466"},"19510":{"id":"19510","name":"Gio Mỹ","slug":"gio-my","fullName":"Xã Gio Mỹ","level":"Xã","parentId":"466"},"19513":{"id":"19513","name":"Vĩnh Trường","slug":"vinh-truong","fullName":"Xã Vĩnh Trường","level":"Xã","parentId":"466"},"19516":{"id":"19516","name":"Gio Bình","slug":"gio-binh","fullName":"Xã Gio Bình","level":"Xã","parentId":"466"},"19519":{"id":"19519","name":"Gio Hải","slug":"gio-hai","fullName":"Xã Gio Hải","level":"Xã","parentId":"466"},"19522":{"id":"19522","name":"Gio An","slug":"gio-an","fullName":"Xã Gio An","level":"Xã","parentId":"466"},"19525":{"id":"19525","name":"Gio Châu","slug":"gio-chau","fullName":"Xã Gio Châu","level":"Xã","parentId":"466"},"19528":{"id":"19528","name":"Gio Thành","slug":"gio-thanh","fullName":"Xã Gio Thành","level":"Xã","parentId":"466"},"19531":{"id":"19531","name":"Gio Việt","slug":"gio-viet","fullName":"Xã Gio Việt","level":"Xã","parentId":"466"},"19534":{"id":"19534","name":"Linh Thượng","slug":"linh-thuong","fullName":"Xã Linh Thượng","level":"Xã","parentId":"466"},"19537":{"id":"19537","name":"Gio Sơn","slug":"gio-son","fullName":"Xã Gio Sơn","level":"Xã","parentId":"466"},"19540":{"id":"19540","name":"Gio Hòa","slug":"gio-hoa","fullName":"Xã Gio Hòa","level":"Xã","parentId":"466"},"19543":{"id":"19543","name":"Gio Mai","slug":"gio-mai","fullName":"Xã Gio Mai","level":"Xã","parentId":"466"},"19546":{"id":"19546","name":"Hải Thái","slug":"hai-thai","fullName":"Xã Hải Thái","level":"Xã","parentId":"466"},"19549":{"id":"19549","name":"Linh Hải","slug":"linh-hai","fullName":"Xã Linh Hải","level":"Xã","parentId":"466"},"19552":{"id":"19552","name":"Gio Quang","slug":"gio-quang","fullName":"Xã Gio Quang","level":"Xã","parentId":"466"}}