{"24736":{"id":"24736","name":"Quảng Trực","slug":"quang-truc","fullName":"Xã Quảng Trực","level":"Xã","parentId":"667"},"24739":{"id":"24739","name":"Đắk Búk So","slug":"dak-buk-so","fullName":"Xã Đắk Búk So","level":"Xã","parentId":"667"},"24740":{"id":"24740","name":"Quảng Tâm","slug":"quang-tam","fullName":"Xã Quảng Tâm","level":"Xã","parentId":"667"},"24742":{"id":"24742","name":"Đắk R\u0027Tíh","slug":"dak-r-tih","fullName":"Xã Đắk R\u0027Tíh","level":"Xã","parentId":"667"},"24746":{"id":"24746","name":"Đắk Ngo","slug":"dak-ngo","fullName":"Xã Đắk Ngo","level":"Xã","parentId":"667"},"24748":{"id":"24748","name":"Quảng Tân","slug":"quang-tan","fullName":"Xã Quảng Tân","level":"Xã","parentId":"667"}}