{"25308":{"id":"25308","name":"Thanh Bình","slug":"thanh-binh","fullName":"Thị trấn Thanh Bình","level":"Thị trấn","parentId":"693"},"25309":{"id":"25309","name":"Hưng Phước","slug":"hung-phuoc","fullName":"Xã Hưng Phước","level":"Xã","parentId":"693"},"25310":{"id":"25310","name":"Phước Thiện","slug":"phuoc-thien","fullName":"Xã Phước Thiện","level":"Xã","parentId":"693"},"25312":{"id":"25312","name":"Thiện Hưng","slug":"thien-hung","fullName":"Xã Thiện Hưng","level":"Xã","parentId":"693"},"25315":{"id":"25315","name":"Thanh Hòa","slug":"thanh-hoa","fullName":"Xã Thanh Hòa","level":"Xã","parentId":"693"},"25318":{"id":"25318","name":"Tân Thành","slug":"tan-thanh","fullName":"Xã Tân Thành","level":"Xã","parentId":"693"},"25321":{"id":"25321","name":"Tân Tiến","slug":"tan-tien","fullName":"Xã Tân Tiến","level":"Xã","parentId":"693"}}