{"25552":{"id":"25552","name":"Dương Minh Châu","slug":"duong-minh-chau","fullName":"Thị trấn Dương Minh Châu","level":"Thị trấn","parentId":"707"},"25555":{"id":"25555","name":"Suối Đá","slug":"suoi-da","fullName":"Xã Suối Đá","level":"Xã","parentId":"707"},"25558":{"id":"25558","name":"Phan","slug":"phan","fullName":"Xã Phan","level":"Xã","parentId":"707"},"25561":{"id":"25561","name":"Phước Ninh","slug":"phuoc-ninh","fullName":"Xã Phước Ninh","level":"Xã","parentId":"707"},"25564":{"id":"25564","name":"Phước Minh","slug":"phuoc-minh","fullName":"Xã Phước Minh","level":"Xã","parentId":"707"},"25567":{"id":"25567","name":"Bàu Năng","slug":"bau-nang","fullName":"Xã Bàu Năng","level":"Xã","parentId":"707"},"25570":{"id":"25570","name":"Chà Là","slug":"cha-la","fullName":"Xã Chà Là","level":"Xã","parentId":"707"},"25573":{"id":"25573","name":"Cầu Khởi","slug":"cau-khoi","fullName":"Xã Cầu Khởi","level":"Xã","parentId":"707"},"25576":{"id":"25576","name":"Bến Củi","slug":"ben-cui","fullName":"Xã Bến Củi","level":"Xã","parentId":"707"},"25579":{"id":"25579","name":"Lộc Ninh","slug":"loc-ninh","fullName":"Xã Lộc Ninh","level":"Xã","parentId":"707"},"25582":{"id":"25582","name":"Truông Mít","slug":"truong-mit","fullName":"Xã Truông Mít","level":"Xã","parentId":"707"}}