{"27796":{"id":"27796","name":"Bình Hòa Tây","slug":"binh-hoa-tay","fullName":"Xã Bình Hòa Tây","level":"Xã","parentId":"798"},"27802":{"id":"27802","name":"Bình Thạnh","slug":"binh-thanh","fullName":"Xã Bình Thạnh","level":"Xã","parentId":"798"},"27808":{"id":"27808","name":"Bình Hòa Trung","slug":"binh-hoa-trung","fullName":"Xã Bình Hòa Trung","level":"Xã","parentId":"798"},"27811":{"id":"27811","name":"Bình Hòa Đông","slug":"binh-hoa-dong","fullName":"Xã Bình Hòa Đông","level":"Xã","parentId":"798"},"27814":{"id":"27814","name":"Bình Phong Thạnh","slug":"binh-phong-thanh","fullName":"Xã Bình Phong Thạnh","level":"Xã","parentId":"798"},"27820":{"id":"27820","name":"Tân Lập","slug":"tan-lap","fullName":"Xã Tân Lập","level":"Xã","parentId":"798"},"27823":{"id":"27823","name":"Tân Thành","slug":"tan-thanh","fullName":"Xã Tân Thành","level":"Xã","parentId":"798"}}