{"31471":{"id":"31471","name":"Thuận An","slug":"thuan-an","fullName":"Phường Thuận An","level":"Phường","parentId":"937"},"31472":{"id":"31472","name":"Trà Lồng","slug":"tra-long","fullName":"Phường Trà Lồng","level":"Phường","parentId":"937"},"31473":{"id":"31473","name":"Bình Thạnh","slug":"binh-thanh","fullName":"Phường Bình Thạnh","level":"Phường","parentId":"937"},"31474":{"id":"31474","name":"Long Bình","slug":"long-binh","fullName":"Xã Long Bình","level":"Xã","parentId":"937"},"31475":{"id":"31475","name":"Vĩnh Tường","slug":"vinh-tuong","fullName":"Phường Vĩnh Tường","level":"Phường","parentId":"937"},"31477":{"id":"31477","name":"Long Trị","slug":"long-tri","fullName":"Xã Long Trị","level":"Xã","parentId":"937"},"31478":{"id":"31478","name":"Long Trị A","slug":"long-tri-a","fullName":"Xã Long Trị A","level":"Xã","parentId":"937"},"31480":{"id":"31480","name":"Long Phú","slug":"long-phu","fullName":"Xã Long Phú","level":"Xã","parentId":"937"},"31481":{"id":"31481","name":"Tân Phú","slug":"tan-phu","fullName":"Xã Tân Phú","level":"Xã","parentId":"937"}}